{"titulo":"Ricardo Delgado advirtió que la economía argentina avanza a dos velocidades y con fuerte heterogeneidad","slug":"ricardo-delgado-economia-argentina-dos-velocidades-heterogenea","resumen":"Ricardo Delgado sostuvo que la economía argentina está funcionando a dos velocidades, con sectores que muestran recuperación y otros que siguen rezagados. El diagnóstico vuelve a poner en foco las diferencias entre actividad, consumo e inversión dentro del proceso económico actual.","contenido":"Ricardo Delgado describió a la economía argentina como un proceso que avanza a dos velocidades, con una dinámica muy heterogénea entre sectores, según publicó Infobae. El diagnóstico apunta a que mientras algunas actividades muestran señales de mejora, otras todavía enfrentan restricciones que limitan su recuperación.\n\nLa mirada del economista se inscribe en un contexto en el que la actividad no se mueve de manera uniforme y donde el comportamiento del consumo, la producción y la inversión presenta diferencias marcadas. Esa disparidad suele reflejarse en la industria, el comercio y los servicios, con desempeños que cambian según la exposición al mercado interno, los costos financieros y la demanda disponible.\n\nEn la práctica, hablar de una economía a dos velocidades implica reconocer que no todos los sectores reaccionan igual frente a un mismo escenario macroeconómico. Algunos rubros logran adaptarse más rápido, mientras otros quedan más rezagados por la presión de precios, la menor capacidad de compra de los hogares o la incertidumbre que afecta las decisiones empresarias.\n\nEl análisis de Delgado también vuelve a instalar una discusión central para la economía argentina: cómo sostener una mejora más pareja y evitar que la recuperación quede concentrada en pocos segmentos. En ese marco, la evolución del ingreso real, la inflación, el crédito y la estabilidad de las reglas económicas seguirán siendo variables clave para determinar si la heterogeneidad actual se reduce o se profundiza.","fuente":"Infobae","categoria":"economia","tags":["economía argentina","actividad económica","heterogeneidad"]}